AUTHORS.rst
CONTRIBUTING.rst
HISTORY.rst
LICENSE
MANIFEST.in
README.rst
setup.cfg
setup.py
docs/Makefile
docs/authors.rst
docs/conf.py
docs/contributing.rst
docs/history.rst
docs/index.rst
docs/installation.rst
docs/make.bat
docs/readme.rst
docs/usage.rst
pyconfiguration/__init__.py
pyconfiguration.egg-info/PKG-INFO
pyconfiguration.egg-info/SOURCES.txt
pyconfiguration.egg-info/dependency_links.txt
pyconfiguration.egg-info/not-zip-safe
pyconfiguration.egg-info/top_level.txt
tests/__init__.py
tests/config1.json
tests/test_pyconfiguration.py