Metadata-Version: 1.1
Name: pyconfiguration
Version: 0.1.1
Summary: Work with config files
Home-page: https://github.com/rain1024/pyconfiguration
Author: Brother Rain
Author-email: brother.rain.1024@gmail.com
License: ISCL
Keywords: pyconfiguration
Platform: UNKNOWN
Classifier: Development Status :: 2 - Pre-Alpha
Classifier: Intended Audience :: Developers
Classifier: License :: OSI Approved :: ISC License (ISCL)
Classifier: Natural Language :: English
Classifier: Programming Language :: Python :: 2
Classifier: Programming Language :: Python :: 2.6
Classifier: Programming Language :: Python :: 2.7
Classifier: Programming Language :: Python :: 3
Classifier: Programming Language :: Python :: 3.3
Classifier: Programming Language :: Python :: 3.4
Classifier: Programming Language :: Python :: 3.5
